transmart_loader/__init__.py
transmart_loader/__version__.py
transmart_loader/collection_validator.py
transmart_loader/collection_visitor.py
transmart_loader/console.py
transmart_loader/copy_writer.py
transmart_loader/csv_types.py
transmart_loader/loader_exception.py
transmart_loader/transmart.py
transmart_loader/tsv_writer.py
transmart_loader-1.4.1.dist-info/LICENSE
transmart_loader-1.4.1.dist-info/METADATA
transmart_loader-1.4.1.dist-info/NOTICE
transmart_loader-1.4.1.dist-info/WHEEL
transmart_loader-1.4.1.dist-info/top_level.txt
transmart_loader-1.4.1.dist-info/RECORD
