Metadata-Version: 2.1
Name: transmart-loader
Version: 1.4.1
Summary: Python library for loading data to TranSMART using transmart-copy
Home-page: https://github.com/thehyve/python_transmart_loader
Author: Gijs Kant
Author-email: gijs@thehyve.nl
License: MIT
Keywords: t,r,a,n,s,m,a,r,t,_,l,o,a,d,e,r
Classifier: Development Status :: 3 - Alpha
Classifier: Intended Audience :: Developers
Classifier: Topic :: Scientific/Engineering :: Bio-Informatics
Classifier: License :: OSI Approved :: MIT License
Classifier: Natural Language :: English
Classifier: Programming Language :: Python :: 3
Classifier: Programming Language :: Python :: 3.7
Classifier: Programming Language :: Python :: 3.8
Classifier: Programming Language :: Python :: 3.9
Classifier: Programming Language :: Python :: 3.10
Requires-Python: >=3.7.0
License-File: LICENSE
License-File: NOTICE
Requires-Dist: importlib-metadata (<4.12,>=4.11)
Requires-Dist: pydantic (<1.11,>=1.10)
Provides-Extra: dev
Requires-Dist: prospector[with_pyroma] ; extra == 'dev'
Requires-Dist: yapf ; extra == 'dev'
Requires-Dist: isort ; extra == 'dev'
